{
  "project_info": {
    "project_number": "852640222104",
    "project_id": "flutter-chat-app-6f6d0",
    "storage_bucket": "flutter-chat-app-6f6d0.firebasestorage.app"
  },
  "client": [
    {
      "client_info": {
        "mobilesdk_app_id": "1:852640222104:android:daa38791bde338032679ed",
        "android_client_info": {
          "package_name": "com.example.chat_app"
        }
      },
      "oauth_client": [],
      "api_key": [
        {
          "current_key": "AIzaSyCIuG26KJoTWA9MxkPJDgcWm_bHDFPJk3o"
        }
      ],
      "services": {
        "appinvite_service": {
          "other_platform_oauth_client": []
        }
      }
    }
  ],
  "configuration_version": "1"
}